tpexe/__init__.py
tpexe/action/__init__.py
tpexe/action/alloc.py
tpexe/action/delete.py
tpexe/conf/__init__.py
tpexe/conf/conf.py
tpexe/login/__init__.py
tpexe/login/login.py
tpexe-1.0.data/data/config.yaml
tpexe-1.0.data/data/run.py
tpexe-1.0.dist-info/METADATA
tpexe-1.0.dist-info/WHEEL
tpexe-1.0.dist-info/top_level.txt
tpexe-1.0.dist-info/RECORD
